[
    {
        "now": "2026-01-16 23:55:46",
        "id": 22494,
        "RecordCode": "CT260115000055",
        "url": "https://ehs.sispark.com.cn:8443/mobile/#/pages/danger/checkTask/patrolRouteList?ctCode=CT260115000055&id=22494",
        "listurl": "https://ehs.sispark.com.cn:8443/api/v2/HDCheckTask/GetApiPageData?ctCode=CT260115000055&currStatus=do&page=0&limit=20&conditions=&dataType=PatrolRouteList"
    },
    {
        "now": "2026-01-16 23:55:47",
        "id": 22494,
        "RecordCode": "CT260115000055",
        "url": "https://ehs.sispark.com.cn:8443/mobile/#/pages/danger/checkTask/patrolRouteList?ctCode=CT260115000055&id=22494",
        "listurl": "https://ehs.sispark.com.cn:8443/api/v2/HDCheckTask/GetApiPageData?ctCode=CT260115000055&currStatus=do&page=0&limit=20&conditions=&dataType=PatrolRouteList"
    },
    {
        "now": "2026-01-16 23:55:47",
        "id": 22494,
        "RecordCode": "CT260115000055",
        "url": "https://ehs.sispark.com.cn:8443/mobile/#/pages/danger/checkTask/patrolRouteList?ctCode=CT260115000055&id=22494",
        "listurl": "https://ehs.sispark.com.cn:8443/api/v2/HDCheckTask/GetApiPageData?ctCode=CT260115000055&currStatus=do&page=0&limit=20&conditions=&dataType=PatrolRouteList"
    },
    {
        "now": "2026-01-16 23:55:47",
        "id": 22494,
        "RecordCode": "CT260115000055",
        "url": "https://ehs.sispark.com.cn:8443/mobile/#/pages/danger/checkTask/patrolRouteList?ctCode=CT260115000055&id=22494",
        "listurl": "https://ehs.sispark.com.cn:8443/api/v2/HDCheckTask/GetApiPageData?ctCode=CT260115000055&currStatus=do&page=0&limit=20&conditions=&dataType=PatrolRouteList"
    },
    {
        "now": "2026-01-16 23:55:48",
        "id": 22494,
        "RecordCode": "CT260115000055",
        "url": "https://ehs.sispark.com.cn:8443/mobile/#/pages/danger/checkTask/patrolRouteList?ctCode=CT260115000055&id=22494",
        "listurl": "https://ehs.sispark.com.cn:8443/api/v2/HDCheckTask/GetApiPageData?ctCode=CT260115000055&currStatus=do&page=0&limit=20&conditions=&dataType=PatrolRouteList"
    },
    {
        "now": "2026-01-16 23:55:49",
        "id": 22494,
        "RecordCode": "CT260115000055",
        "url": "https://ehs.sispark.com.cn:8443/mobile/#/pages/danger/checkTask/patrolRouteList?ctCode=CT260115000055&id=22494",
        "listurl": "https://ehs.sispark.com.cn:8443/api/v2/HDCheckTask/GetApiPageData?ctCode=CT260115000055&currStatus=do&page=0&limit=20&conditions=&dataType=PatrolRouteList"
    },
    {
        "now": "2026-01-16 23:55:49",
        "id": 22494,
        "RecordCode": "CT260115000055",
        "url": "https://ehs.sispark.com.cn:8443/mobile/#/pages/danger/checkTask/patrolRouteList?ctCode=CT260115000055&id=22494",
        "listurl": "https://ehs.sispark.com.cn:8443/api/v2/HDCheckTask/GetApiPageData?ctCode=CT260115000055&currStatus=do&page=0&limit=20&conditions=&dataType=PatrolRouteList"
    },
    {
        "now": "2026-01-16 23:55:49",
        "id": 22494,
        "RecordCode": "CT260115000055",
        "url": "https://ehs.sispark.com.cn:8443/mobile/#/pages/danger/checkTask/patrolRouteList?ctCode=CT260115000055&id=22494",
        "listurl": "https://ehs.sispark.com.cn:8443/api/v2/HDCheckTask/GetApiPageData?ctCode=CT260115000055&currStatus=do&page=0&limit=20&conditions=&dataType=PatrolRouteList"
    },
    {
        "now": "2026-01-16 23:55:49",
        "id": 22494,
        "RecordCode": "CT260115000055",
        "url": "https://ehs.sispark.com.cn:8443/mobile/#/pages/danger/checkTask/patrolRouteList?ctCode=CT260115000055&id=22494",
        "listurl": "https://ehs.sispark.com.cn:8443/api/v2/HDCheckTask/GetApiPageData?ctCode=CT260115000055&currStatus=do&page=0&limit=20&conditions=&dataType=PatrolRouteList"
    },
    {
        "now": "2026-01-16 23:55:49",
        "id": 22494,
        "RecordCode": "CT260115000055",
        "url": "https://ehs.sispark.com.cn:8443/mobile/#/pages/danger/checkTask/patrolRouteList?ctCode=CT260115000055&id=22494",
        "listurl": "https://ehs.sispark.com.cn:8443/api/v2/HDCheckTask/GetApiPageData?ctCode=CT260115000055&currStatus=do&page=0&limit=20&conditions=&dataType=PatrolRouteList"
    },
    {
        "now": "2026-01-16 23:55:50",
        "id": 22494,
        "RecordCode": "CT260115000055",
        "url": "https://ehs.sispark.com.cn:8443/mobile/#/pages/danger/checkTask/patrolRouteList?ctCode=CT260115000055&id=22494",
        "listurl": "https://ehs.sispark.com.cn:8443/api/v2/HDCheckTask/GetApiPageData?ctCode=CT260115000055&currStatus=do&page=0&limit=20&conditions=&dataType=PatrolRouteList"
    },
    {
        "now": "2026-01-16 23:55:51",
        "id": 22494,
        "RecordCode": "CT260115000055",
        "url": "https://ehs.sispark.com.cn:8443/mobile/#/pages/danger/checkTask/patrolRouteList?ctCode=CT260115000055&id=22494",
        "listurl": "https://ehs.sispark.com.cn:8443/api/v2/HDCheckTask/GetApiPageData?ctCode=CT260115000055&currStatus=do&page=0&limit=20&conditions=&dataType=PatrolRouteList"
    },
    {
        "now": "2026-01-16 23:55:51",
        "id": 22494,
        "RecordCode": "CT260115000055",
        "url": "https://ehs.sispark.com.cn:8443/mobile/#/pages/danger/checkTask/patrolRouteList?ctCode=CT260115000055&id=22494",
        "listurl": "https://ehs.sispark.com.cn:8443/api/v2/HDCheckTask/GetApiPageData?ctCode=CT260115000055&currStatus=do&page=0&limit=20&conditions=&dataType=PatrolRouteList"
    },
    {
        "now": "2026-01-16 23:55:52",
        "id": 22494,
        "RecordCode": "CT260115000055",
        "url": "https://ehs.sispark.com.cn:8443/mobile/#/pages/danger/checkTask/patrolRouteList?ctCode=CT260115000055&id=22494",
        "listurl": "https://ehs.sispark.com.cn:8443/api/v2/HDCheckTask/GetApiPageData?ctCode=CT260115000055&currStatus=do&page=0&limit=20&conditions=&dataType=PatrolRouteList"
    },
    {
        "now": "2026-01-16 23:55:54",
        "id": 22494,
        "RecordCode": "CT260115000055",
        "url": "https://ehs.sispark.com.cn:8443/mobile/#/pages/danger/checkTask/patrolRouteList?ctCode=CT260115000055&id=22494",
        "listurl": "https://ehs.sispark.com.cn:8443/api/v2/HDCheckTask/GetApiPageData?ctCode=CT260115000055&currStatus=do&page=0&limit=20&conditions=&dataType=PatrolRouteList"
    },
    {
        "now": "2026-01-16 23:56:00",
        "id": 22494,
        "RecordCode": "CT260115000055",
        "url": "https://ehs.sispark.com.cn:8443/mobile/#/pages/danger/checkTask/patrolRouteList?ctCode=CT260115000055&id=22494",
        "listurl": "https://ehs.sispark.com.cn:8443/api/v2/HDCheckTask/GetApiPageData?ctCode=CT260115000055&currStatus=do&page=0&limit=20&conditions=&dataType=PatrolRouteList"
    },
    {
        "now": "2026-01-16 23:56:01",
        "id": 22494,
        "RecordCode": "CT260115000055",
        "url": "https://ehs.sispark.com.cn:8443/mobile/#/pages/danger/checkTask/patrolRouteList?ctCode=CT260115000055&id=22494",
        "listurl": "https://ehs.sispark.com.cn:8443/api/v2/HDCheckTask/GetApiPageData?ctCode=CT260115000055&currStatus=do&page=0&limit=20&conditions=&dataType=PatrolRouteList"
    },
    {
        "now": "2026-01-16 23:56:03",
        "id": 22494,
        "RecordCode": "CT260115000055",
        "url": "https://ehs.sispark.com.cn:8443/mobile/#/pages/danger/checkTask/patrolRouteList?ctCode=CT260115000055&id=22494",
        "listurl": "https://ehs.sispark.com.cn:8443/api/v2/HDCheckTask/GetApiPageData?ctCode=CT260115000055&currStatus=do&page=0&limit=20&conditions=&dataType=PatrolRouteList"
    },
    {
        "now": "2026-01-16 23:56:05",
        "id": 22494,
        "RecordCode": "CT260115000055",
        "url": "https://ehs.sispark.com.cn:8443/mobile/#/pages/danger/checkTask/patrolRouteList?ctCode=CT260115000055&id=22494",
        "listurl": "https://ehs.sispark.com.cn:8443/api/v2/HDCheckTask/GetApiPageData?ctCode=CT260115000055&currStatus=do&page=0&limit=20&conditions=&dataType=PatrolRouteList"
    },
    {
        "now": "2026-01-16 23:56:10",
        "id": 22494,
        "RecordCode": "CT260115000055",
        "url": "https://ehs.sispark.com.cn:8443/mobile/#/pages/danger/checkTask/patrolRouteList?ctCode=CT260115000055&id=22494",
        "listurl": "https://ehs.sispark.com.cn:8443/api/v2/HDCheckTask/GetApiPageData?ctCode=CT260115000055&currStatus=do&page=0&limit=20&conditions=&dataType=PatrolRouteList"
    },
    {
        "now": "2026-01-16 23:56:13",
        "id": 22494,
        "RecordCode": "CT260115000055",
        "url": "https://ehs.sispark.com.cn:8443/mobile/#/pages/danger/checkTask/patrolRouteList?ctCode=CT260115000055&id=22494",
        "listurl": "https://ehs.sispark.com.cn:8443/api/v2/HDCheckTask/GetApiPageData?ctCode=CT260115000055&currStatus=do&page=0&limit=20&conditions=&dataType=PatrolRouteList"
    },
    {
        "now": "2026-01-16 23:56:14",
        "id": 22494,
        "RecordCode": "CT260115000055",
        "url": "https://ehs.sispark.com.cn:8443/mobile/#/pages/danger/checkTask/patrolRouteList?ctCode=CT260115000055&id=22494",
        "listurl": "https://ehs.sispark.com.cn:8443/api/v2/HDCheckTask/GetApiPageData?ctCode=CT260115000055&currStatus=do&page=0&limit=20&conditions=&dataType=PatrolRouteList"
    },
    {
        "now": "2026-01-16 23:56:14",
        "id": 22494,
        "RecordCode": "CT260115000055",
        "url": "https://ehs.sispark.com.cn:8443/mobile/#/pages/danger/checkTask/patrolRouteList?ctCode=CT260115000055&id=22494",
        "listurl": "https://ehs.sispark.com.cn:8443/api/v2/HDCheckTask/GetApiPageData?ctCode=CT260115000055&currStatus=do&page=0&limit=20&conditions=&dataType=PatrolRouteList"
    },
    {
        "now": "2026-01-16 23:56:16",
        "id": 22494,
        "RecordCode": "CT260115000055",
        "url": "https://ehs.sispark.com.cn:8443/mobile/#/pages/danger/checkTask/patrolRouteList?ctCode=CT260115000055&id=22494",
        "listurl": "https://ehs.sispark.com.cn:8443/api/v2/HDCheckTask/GetApiPageData?ctCode=CT260115000055&currStatus=do&page=0&limit=20&conditions=&dataType=PatrolRouteList"
    },
    {
        "now": "2026-01-16 23:56:21",
        "id": 22494,
        "RecordCode": "CT260115000055",
        "url": "https://ehs.sispark.com.cn:8443/mobile/#/pages/danger/checkTask/patrolRouteList?ctCode=CT260115000055&id=22494",
        "listurl": "https://ehs.sispark.com.cn:8443/api/v2/HDCheckTask/GetApiPageData?ctCode=CT260115000055&currStatus=do&page=0&limit=20&conditions=&dataType=PatrolRouteList"
    },
    {
        "now": "2026-01-16 23:56:21",
        "id": 22494,
        "RecordCode": "CT260115000055",
        "url": "https://ehs.sispark.com.cn:8443/mobile/#/pages/danger/checkTask/patrolRouteList?ctCode=CT260115000055&id=22494",
        "listurl": "https://ehs.sispark.com.cn:8443/api/v2/HDCheckTask/GetApiPageData?ctCode=CT260115000055&currStatus=do&page=0&limit=20&conditions=&dataType=PatrolRouteList"
    },
    {
        "now": "2026-01-16 23:56:26",
        "id": 22494,
        "RecordCode": "CT260115000055",
        "url": "https://ehs.sispark.com.cn:8443/mobile/#/pages/danger/checkTask/patrolRouteList?ctCode=CT260115000055&id=22494",
        "listurl": "https://ehs.sispark.com.cn:8443/api/v2/HDCheckTask/GetApiPageData?ctCode=CT260115000055&currStatus=do&page=0&limit=20&conditions=&dataType=PatrolRouteList"
    },
    {
        "now": "2026-01-16 23:56:32",
        "id": 22494,
        "RecordCode": "CT260115000055",
        "url": "https://ehs.sispark.com.cn:8443/mobile/#/pages/danger/checkTask/patrolRouteList?ctCode=CT260115000055&id=22494",
        "listurl": "https://ehs.sispark.com.cn:8443/api/v2/HDCheckTask/GetApiPageData?ctCode=CT260115000055&currStatus=do&page=0&limit=20&conditions=&dataType=PatrolRouteList"
    },
    {
        "now": "2026-01-16 23:56:37",
        "id": 22494,
        "RecordCode": "CT260115000055",
        "url": "https://ehs.sispark.com.cn:8443/mobile/#/pages/danger/checkTask/patrolRouteList?ctCode=CT260115000055&id=22494",
        "listurl": "https://ehs.sispark.com.cn:8443/api/v2/HDCheckTask/GetApiPageData?ctCode=CT260115000055&currStatus=do&page=0&limit=20&conditions=&dataType=PatrolRouteList"
    },
    {
        "now": "2026-01-16 23:56:38",
        "id": 22494,
        "RecordCode": "CT260115000055",
        "url": "https://ehs.sispark.com.cn:8443/mobile/#/pages/danger/checkTask/patrolRouteList?ctCode=CT260115000055&id=22494",
        "listurl": "https://ehs.sispark.com.cn:8443/api/v2/HDCheckTask/GetApiPageData?ctCode=CT260115000055&currStatus=do&page=0&limit=20&conditions=&dataType=PatrolRouteList"
    },
    {
        "now": "2026-01-16 23:56:43",
        "id": 22494,
        "RecordCode": "CT260115000055",
        "url": "https://ehs.sispark.com.cn:8443/mobile/#/pages/danger/checkTask/patrolRouteList?ctCode=CT260115000055&id=22494",
        "listurl": "https://ehs.sispark.com.cn:8443/api/v2/HDCheckTask/GetApiPageData?ctCode=CT260115000055&currStatus=do&page=0&limit=20&conditions=&dataType=PatrolRouteList"
    },
    {
        "now": "2026-01-16 23:56:47",
        "id": 22494,
        "RecordCode": "CT260115000055",
        "url": "https://ehs.sispark.com.cn:8443/mobile/#/pages/danger/checkTask/patrolRouteList?ctCode=CT260115000055&id=22494",
        "listurl": "https://ehs.sispark.com.cn:8443/api/v2/HDCheckTask/GetApiPageData?ctCode=CT260115000055&currStatus=do&page=0&limit=20&conditions=&dataType=PatrolRouteList"
    },
    {
        "now": "2026-01-16 23:56:47",
        "id": 22494,
        "RecordCode": "CT260115000055",
        "url": "https://ehs.sispark.com.cn:8443/mobile/#/pages/danger/checkTask/patrolRouteList?ctCode=CT260115000055&id=22494",
        "listurl": "https://ehs.sispark.com.cn:8443/api/v2/HDCheckTask/GetApiPageData?ctCode=CT260115000055&currStatus=do&page=0&limit=20&conditions=&dataType=PatrolRouteList"
    },
    {
        "now": "2026-01-16 23:56:47",
        "id": 22494,
        "RecordCode": "CT260115000055",
        "url": "https://ehs.sispark.com.cn:8443/mobile/#/pages/danger/checkTask/patrolRouteList?ctCode=CT260115000055&id=22494",
        "listurl": "https://ehs.sispark.com.cn:8443/api/v2/HDCheckTask/GetApiPageData?ctCode=CT260115000055&currStatus=do&page=0&limit=20&conditions=&dataType=PatrolRouteList"
    },
    {
        "now": "2026-01-16 23:56:48",
        "id": 22494,
        "RecordCode": "CT260115000055",
        "url": "https://ehs.sispark.com.cn:8443/mobile/#/pages/danger/checkTask/patrolRouteList?ctCode=CT260115000055&id=22494",
        "listurl": "https://ehs.sispark.com.cn:8443/api/v2/HDCheckTask/GetApiPageData?ctCode=CT260115000055&currStatus=do&page=0&limit=20&conditions=&dataType=PatrolRouteList"
    },
    {
        "now": "2026-01-16 23:56:48",
        "id": 22494,
        "RecordCode": "CT260115000055",
        "url": "https://ehs.sispark.com.cn:8443/mobile/#/pages/danger/checkTask/patrolRouteList?ctCode=CT260115000055&id=22494",
        "listurl": "https://ehs.sispark.com.cn:8443/api/v2/HDCheckTask/GetApiPageData?ctCode=CT260115000055&currStatus=do&page=0&limit=20&conditions=&dataType=PatrolRouteList"
    },
    {
        "now": "2026-01-16 23:56:48",
        "id": 22494,
        "RecordCode": "CT260115000055",
        "url": "https://ehs.sispark.com.cn:8443/mobile/#/pages/danger/checkTask/patrolRouteList?ctCode=CT260115000055&id=22494",
        "listurl": "https://ehs.sispark.com.cn:8443/api/v2/HDCheckTask/GetApiPageData?ctCode=CT260115000055&currStatus=do&page=0&limit=20&conditions=&dataType=PatrolRouteList"
    },
    {
        "now": "2026-01-16 23:56:48",
        "id": 22494,
        "RecordCode": "CT260115000055",
        "url": "https://ehs.sispark.com.cn:8443/mobile/#/pages/danger/checkTask/patrolRouteList?ctCode=CT260115000055&id=22494",
        "listurl": "https://ehs.sispark.com.cn:8443/api/v2/HDCheckTask/GetApiPageData?ctCode=CT260115000055&currStatus=do&page=0&limit=20&conditions=&dataType=PatrolRouteList"
    },
    {
        "now": "2026-01-16 23:56:48",
        "id": 22494,
        "RecordCode": "CT260115000055",
        "url": "https://ehs.sispark.com.cn:8443/mobile/#/pages/danger/checkTask/patrolRouteList?ctCode=CT260115000055&id=22494",
        "listurl": "https://ehs.sispark.com.cn:8443/api/v2/HDCheckTask/GetApiPageData?ctCode=CT260115000055&currStatus=do&page=0&limit=20&conditions=&dataType=PatrolRouteList"
    },
    {
        "now": "2026-01-16 23:56:49",
        "id": 22494,
        "RecordCode": "CT260115000055",
        "url": "https://ehs.sispark.com.cn:8443/mobile/#/pages/danger/checkTask/patrolRouteList?ctCode=CT260115000055&id=22494",
        "listurl": "https://ehs.sispark.com.cn:8443/api/v2/HDCheckTask/GetApiPageData?ctCode=CT260115000055&currStatus=do&page=0&limit=20&conditions=&dataType=PatrolRouteList"
    },
    {
        "now": "2026-01-16 23:56:49",
        "id": 22494,
        "RecordCode": "CT260115000055",
        "url": "https://ehs.sispark.com.cn:8443/mobile/#/pages/danger/checkTask/patrolRouteList?ctCode=CT260115000055&id=22494",
        "listurl": "https://ehs.sispark.com.cn:8443/api/v2/HDCheckTask/GetApiPageData?ctCode=CT260115000055&currStatus=do&page=0&limit=20&conditions=&dataType=PatrolRouteList"
    },
    {
        "now": "2026-01-16 23:56:49",
        "id": 22494,
        "RecordCode": "CT260115000055",
        "url": "https://ehs.sispark.com.cn:8443/mobile/#/pages/danger/checkTask/patrolRouteList?ctCode=CT260115000055&id=22494",
        "listurl": "https://ehs.sispark.com.cn:8443/api/v2/HDCheckTask/GetApiPageData?ctCode=CT260115000055&currStatus=do&page=0&limit=20&conditions=&dataType=PatrolRouteList"
    },
    {
        "now": "2026-01-16 23:56:49",
        "id": 22494,
        "RecordCode": "CT260115000055",
        "url": "https://ehs.sispark.com.cn:8443/mobile/#/pages/danger/checkTask/patrolRouteList?ctCode=CT260115000055&id=22494",
        "listurl": "https://ehs.sispark.com.cn:8443/api/v2/HDCheckTask/GetApiPageData?ctCode=CT260115000055&currStatus=do&page=0&limit=20&conditions=&dataType=PatrolRouteList"
    },
    {
        "now": "2026-01-16 23:56:51",
        "id": 22494,
        "RecordCode": "CT260115000055",
        "url": "https://ehs.sispark.com.cn:8443/mobile/#/pages/danger/checkTask/patrolRouteList?ctCode=CT260115000055&id=22494",
        "listurl": "https://ehs.sispark.com.cn:8443/api/v2/HDCheckTask/GetApiPageData?ctCode=CT260115000055&currStatus=do&page=0&limit=20&conditions=&dataType=PatrolRouteList"
    },
    {
        "now": "2026-01-16 23:56:52",
        "id": 22494,
        "RecordCode": "CT260115000055",
        "url": "https://ehs.sispark.com.cn:8443/mobile/#/pages/danger/checkTask/patrolRouteList?ctCode=CT260115000055&id=22494",
        "listurl": "https://ehs.sispark.com.cn:8443/api/v2/HDCheckTask/GetApiPageData?ctCode=CT260115000055&currStatus=do&page=0&limit=20&conditions=&dataType=PatrolRouteList"
    },
    {
        "now": "2026-01-16 23:56:52",
        "id": 22494,
        "RecordCode": "CT260115000055",
        "url": "https://ehs.sispark.com.cn:8443/mobile/#/pages/danger/checkTask/patrolRouteList?ctCode=CT260115000055&id=22494",
        "listurl": "https://ehs.sispark.com.cn:8443/api/v2/HDCheckTask/GetApiPageData?ctCode=CT260115000055&currStatus=do&page=0&limit=20&conditions=&dataType=PatrolRouteList"
    },
    {
        "now": "2026-01-16 23:56:52",
        "id": 22494,
        "RecordCode": "CT260115000055",
        "url": "https://ehs.sispark.com.cn:8443/mobile/#/pages/danger/checkTask/patrolRouteList?ctCode=CT260115000055&id=22494",
        "listurl": "https://ehs.sispark.com.cn:8443/api/v2/HDCheckTask/GetApiPageData?ctCode=CT260115000055&currStatus=do&page=0&limit=20&conditions=&dataType=PatrolRouteList"
    },
    {
        "now": "2026-01-16 23:56:53",
        "id": 22494,
        "RecordCode": "CT260115000055",
        "url": "https://ehs.sispark.com.cn:8443/mobile/#/pages/danger/checkTask/patrolRouteList?ctCode=CT260115000055&id=22494",
        "listurl": "https://ehs.sispark.com.cn:8443/api/v2/HDCheckTask/GetApiPageData?ctCode=CT260115000055&currStatus=do&page=0&limit=20&conditions=&dataType=PatrolRouteList"
    },
    {
        "now": "2026-01-16 23:56:59",
        "id": 22494,
        "RecordCode": "CT260115000055",
        "url": "https://ehs.sispark.com.cn:8443/mobile/#/pages/danger/checkTask/patrolRouteList?ctCode=CT260115000055&id=22494",
        "listurl": "https://ehs.sispark.com.cn:8443/api/v2/HDCheckTask/GetApiPageData?ctCode=CT260115000055&currStatus=do&page=0&limit=20&conditions=&dataType=PatrolRouteList"
    },
    {
        "now": "2026-01-16 23:57:02",
        "id": 22494,
        "RecordCode": "CT260115000055",
        "url": "https://ehs.sispark.com.cn:8443/mobile/#/pages/danger/checkTask/patrolRouteList?ctCode=CT260115000055&id=22494",
        "listurl": "https://ehs.sispark.com.cn:8443/api/v2/HDCheckTask/GetApiPageData?ctCode=CT260115000055&currStatus=do&page=0&limit=20&conditions=&dataType=PatrolRouteList"
    },
    {
        "now": "2026-01-16 23:57:03",
        "id": 22494,
        "RecordCode": "CT260115000055",
        "url": "https://ehs.sispark.com.cn:8443/mobile/#/pages/danger/checkTask/patrolRouteList?ctCode=CT260115000055&id=22494",
        "listurl": "https://ehs.sispark.com.cn:8443/api/v2/HDCheckTask/GetApiPageData?ctCode=CT260115000055&currStatus=do&page=0&limit=20&conditions=&dataType=PatrolRouteList"
    },
    {
        "now": "2026-01-16 23:57:04",
        "id": 22494,
        "RecordCode": "CT260115000055",
        "url": "https://ehs.sispark.com.cn:8443/mobile/#/pages/danger/checkTask/patrolRouteList?ctCode=CT260115000055&id=22494",
        "listurl": "https://ehs.sispark.com.cn:8443/api/v2/HDCheckTask/GetApiPageData?ctCode=CT260115000055&currStatus=do&page=0&limit=20&conditions=&dataType=PatrolRouteList"
    },
    {
        "now": "2026-01-16 23:57:10",
        "id": 22494,
        "RecordCode": "CT260115000055",
        "url": "https://ehs.sispark.com.cn:8443/mobile/#/pages/danger/checkTask/patrolRouteList?ctCode=CT260115000055&id=22494",
        "listurl": "https://ehs.sispark.com.cn:8443/api/v2/HDCheckTask/GetApiPageData?ctCode=CT260115000055&currStatus=do&page=0&limit=20&conditions=&dataType=PatrolRouteList"
    },
    {
        "now": "2026-01-16 23:57:14",
        "id": 22494,
        "RecordCode": "CT260115000055",
        "url": "https://ehs.sispark.com.cn:8443/mobile/#/pages/danger/checkTask/patrolRouteList?ctCode=CT260115000055&id=22494",
        "listurl": "https://ehs.sispark.com.cn:8443/api/v2/HDCheckTask/GetApiPageData?ctCode=CT260115000055&currStatus=do&page=0&limit=20&conditions=&dataType=PatrolRouteList"
    },
    {
        "now": "2026-01-16 23:57:15",
        "id": 22494,
        "RecordCode": "CT260115000055",
        "url": "https://ehs.sispark.com.cn:8443/mobile/#/pages/danger/checkTask/patrolRouteList?ctCode=CT260115000055&id=22494",
        "listurl": "https://ehs.sispark.com.cn:8443/api/v2/HDCheckTask/GetApiPageData?ctCode=CT260115000055&currStatus=do&page=0&limit=20&conditions=&dataType=PatrolRouteList"
    },
    {
        "now": "2026-01-16 23:57:15",
        "id": 22494,
        "RecordCode": "CT260115000055",
        "url": "https://ehs.sispark.com.cn:8443/mobile/#/pages/danger/checkTask/patrolRouteList?ctCode=CT260115000055&id=22494",
        "listurl": "https://ehs.sispark.com.cn:8443/api/v2/HDCheckTask/GetApiPageData?ctCode=CT260115000055&currStatus=do&page=0&limit=20&conditions=&dataType=PatrolRouteList"
    },
    {
        "now": "2026-01-16 23:57:15",
        "id": 22494,
        "RecordCode": "CT260115000055",
        "url": "https://ehs.sispark.com.cn:8443/mobile/#/pages/danger/checkTask/patrolRouteList?ctCode=CT260115000055&id=22494",
        "listurl": "https://ehs.sispark.com.cn:8443/api/v2/HDCheckTask/GetApiPageData?ctCode=CT260115000055&currStatus=do&page=0&limit=20&conditions=&dataType=PatrolRouteList"
    },
    {
        "now": "2026-01-16 23:57:20",
        "id": 22494,
        "RecordCode": "CT260115000055",
        "url": "https://ehs.sispark.com.cn:8443/mobile/#/pages/danger/checkTask/patrolRouteList?ctCode=CT260115000055&id=22494",
        "listurl": "https://ehs.sispark.com.cn:8443/api/v2/HDCheckTask/GetApiPageData?ctCode=CT260115000055&currStatus=do&page=0&limit=20&conditions=&dataType=PatrolRouteList"
    },
    {
        "now": "2026-01-16 23:57:21",
        "id": 22494,
        "RecordCode": "CT260115000055",
        "url": "https://ehs.sispark.com.cn:8443/mobile/#/pages/danger/checkTask/patrolRouteList?ctCode=CT260115000055&id=22494",
        "listurl": "https://ehs.sispark.com.cn:8443/api/v2/HDCheckTask/GetApiPageData?ctCode=CT260115000055&currStatus=do&page=0&limit=20&conditions=&dataType=PatrolRouteList"
    },
    {
        "now": "2026-01-16 23:57:26",
        "id": 22494,
        "RecordCode": "CT260115000055",
        "url": "https://ehs.sispark.com.cn:8443/mobile/#/pages/danger/checkTask/patrolRouteList?ctCode=CT260115000055&id=22494",
        "listurl": "https://ehs.sispark.com.cn:8443/api/v2/HDCheckTask/GetApiPageData?ctCode=CT260115000055&currStatus=do&page=0&limit=20&conditions=&dataType=PatrolRouteList"
    },
    {
        "now": "2026-01-16 23:57:31",
        "id": 22494,
        "RecordCode": "CT260115000055",
        "url": "https://ehs.sispark.com.cn:8443/mobile/#/pages/danger/checkTask/patrolRouteList?ctCode=CT260115000055&id=22494",
        "listurl": "https://ehs.sispark.com.cn:8443/api/v2/HDCheckTask/GetApiPageData?ctCode=CT260115000055&currStatus=do&page=0&limit=20&conditions=&dataType=PatrolRouteList"
    },
    {
        "now": "2026-01-16 23:57:37",
        "id": 22494,
        "RecordCode": "CT260115000055",
        "url": "https://ehs.sispark.com.cn:8443/mobile/#/pages/danger/checkTask/patrolRouteList?ctCode=CT260115000055&id=22494",
        "listurl": "https://ehs.sispark.com.cn:8443/api/v2/HDCheckTask/GetApiPageData?ctCode=CT260115000055&currStatus=do&page=0&limit=20&conditions=&dataType=PatrolRouteList"
    },
    {
        "now": "2026-01-16 23:57:38",
        "id": 22494,
        "RecordCode": "CT260115000055",
        "url": "https://ehs.sispark.com.cn:8443/mobile/#/pages/danger/checkTask/patrolRouteList?ctCode=CT260115000055&id=22494",
        "listurl": "https://ehs.sispark.com.cn:8443/api/v2/HDCheckTask/GetApiPageData?ctCode=CT260115000055&currStatus=do&page=0&limit=20&conditions=&dataType=PatrolRouteList"
    },
    {
        "now": "2026-01-16 23:57:42",
        "id": 22494,
        "RecordCode": "CT260115000055",
        "url": "https://ehs.sispark.com.cn:8443/mobile/#/pages/danger/checkTask/patrolRouteList?ctCode=CT260115000055&id=22494",
        "listurl": "https://ehs.sispark.com.cn:8443/api/v2/HDCheckTask/GetApiPageData?ctCode=CT260115000055&currStatus=do&page=0&limit=20&conditions=&dataType=PatrolRouteList"
    },
    {
        "now": "2026-01-16 23:57:47",
        "id": 22494,
        "RecordCode": "CT260115000055",
        "url": "https://ehs.sispark.com.cn:8443/mobile/#/pages/danger/checkTask/patrolRouteList?ctCode=CT260115000055&id=22494",
        "listurl": "https://ehs.sispark.com.cn:8443/api/v2/HDCheckTask/GetApiPageData?ctCode=CT260115000055&currStatus=do&page=0&limit=20&conditions=&dataType=PatrolRouteList"
    },
    {
        "now": "2026-01-16 23:57:47",
        "id": 22494,
        "RecordCode": "CT260115000055",
        "url": "https://ehs.sispark.com.cn:8443/mobile/#/pages/danger/checkTask/patrolRouteList?ctCode=CT260115000055&id=22494",
        "listurl": "https://ehs.sispark.com.cn:8443/api/v2/HDCheckTask/GetApiPageData?ctCode=CT260115000055&currStatus=do&page=0&limit=20&conditions=&dataType=PatrolRouteList"
    },
    {
        "now": "2026-01-16 23:57:47",
        "id": 22494,
        "RecordCode": "CT260115000055",
        "url": "https://ehs.sispark.com.cn:8443/mobile/#/pages/danger/checkTask/patrolRouteList?ctCode=CT260115000055&id=22494",
        "listurl": "https://ehs.sispark.com.cn:8443/api/v2/HDCheckTask/GetApiPageData?ctCode=CT260115000055&currStatus=do&page=0&limit=20&conditions=&dataType=PatrolRouteList"
    },
    {
        "now": "2026-01-16 23:57:48",
        "id": 22494,
        "RecordCode": "CT260115000055",
        "url": "https://ehs.sispark.com.cn:8443/mobile/#/pages/danger/checkTask/patrolRouteList?ctCode=CT260115000055&id=22494",
        "listurl": "https://ehs.sispark.com.cn:8443/api/v2/HDCheckTask/GetApiPageData?ctCode=CT260115000055&currStatus=do&page=0&limit=20&conditions=&dataType=PatrolRouteList"
    },
    {
        "now": "2026-01-16 23:57:48",
        "id": 22494,
        "RecordCode": "CT260115000055",
        "url": "https://ehs.sispark.com.cn:8443/mobile/#/pages/danger/checkTask/patrolRouteList?ctCode=CT260115000055&id=22494",
        "listurl": "https://ehs.sispark.com.cn:8443/api/v2/HDCheckTask/GetApiPageData?ctCode=CT260115000055&currStatus=do&page=0&limit=20&conditions=&dataType=PatrolRouteList"
    },
    {
        "now": "2026-01-16 23:57:48",
        "id": 22494,
        "RecordCode": "CT260115000055",
        "url": "https://ehs.sispark.com.cn:8443/mobile/#/pages/danger/checkTask/patrolRouteList?ctCode=CT260115000055&id=22494",
        "listurl": "https://ehs.sispark.com.cn:8443/api/v2/HDCheckTask/GetApiPageData?ctCode=CT260115000055&currStatus=do&page=0&limit=20&conditions=&dataType=PatrolRouteList"
    },
    {
        "now": "2026-01-16 23:57:49",
        "id": 22494,
        "RecordCode": "CT260115000055",
        "url": "https://ehs.sispark.com.cn:8443/mobile/#/pages/danger/checkTask/patrolRouteList?ctCode=CT260115000055&id=22494",
        "listurl": "https://ehs.sispark.com.cn:8443/api/v2/HDCheckTask/GetApiPageData?ctCode=CT260115000055&currStatus=do&page=0&limit=20&conditions=&dataType=PatrolRouteList"
    },
    {
        "now": "2026-01-16 23:57:49",
        "id": 22494,
        "RecordCode": "CT260115000055",
        "url": "https://ehs.sispark.com.cn:8443/mobile/#/pages/danger/checkTask/patrolRouteList?ctCode=CT260115000055&id=22494",
        "listurl": "https://ehs.sispark.com.cn:8443/api/v2/HDCheckTask/GetApiPageData?ctCode=CT260115000055&currStatus=do&page=0&limit=20&conditions=&dataType=PatrolRouteList"
    },
    {
        "now": "2026-01-16 23:57:50",
        "id": 22494,
        "RecordCode": "CT260115000055",
        "url": "https://ehs.sispark.com.cn:8443/mobile/#/pages/danger/checkTask/patrolRouteList?ctCode=CT260115000055&id=22494",
        "listurl": "https://ehs.sispark.com.cn:8443/api/v2/HDCheckTask/GetApiPageData?ctCode=CT260115000055&currStatus=do&page=0&limit=20&conditions=&dataType=PatrolRouteList"
    },
    {
        "now": "2026-01-16 23:57:50",
        "id": 22494,
        "RecordCode": "CT260115000055",
        "url": "https://ehs.sispark.com.cn:8443/mobile/#/pages/danger/checkTask/patrolRouteList?ctCode=CT260115000055&id=22494",
        "listurl": "https://ehs.sispark.com.cn:8443/api/v2/HDCheckTask/GetApiPageData?ctCode=CT260115000055&currStatus=do&page=0&limit=20&conditions=&dataType=PatrolRouteList"
    },
    {
        "now": "2026-01-16 23:57:50",
        "id": 22494,
        "RecordCode": "CT260115000055",
        "url": "https://ehs.sispark.com.cn:8443/mobile/#/pages/danger/checkTask/patrolRouteList?ctCode=CT260115000055&id=22494",
        "listurl": "https://ehs.sispark.com.cn:8443/api/v2/HDCheckTask/GetApiPageData?ctCode=CT260115000055&currStatus=do&page=0&limit=20&conditions=&dataType=PatrolRouteList"
    },
    {
        "now": "2026-01-16 23:57:50",
        "id": 22494,
        "RecordCode": "CT260115000055",
        "url": "https://ehs.sispark.com.cn:8443/mobile/#/pages/danger/checkTask/patrolRouteList?ctCode=CT260115000055&id=22494",
        "listurl": "https://ehs.sispark.com.cn:8443/api/v2/HDCheckTask/GetApiPageData?ctCode=CT260115000055&currStatus=do&page=0&limit=20&conditions=&dataType=PatrolRouteList"
    },
    {
        "now": "2026-01-16 23:57:51",
        "id": 22494,
        "RecordCode": "CT260115000055",
        "url": "https://ehs.sispark.com.cn:8443/mobile/#/pages/danger/checkTask/patrolRouteList?ctCode=CT260115000055&id=22494",
        "listurl": "https://ehs.sispark.com.cn:8443/api/v2/HDCheckTask/GetApiPageData?ctCode=CT260115000055&currStatus=do&page=0&limit=20&conditions=&dataType=PatrolRouteList"
    },
    {
        "now": "2026-01-16 23:57:52",
        "id": 22494,
        "RecordCode": "CT260115000055",
        "url": "https://ehs.sispark.com.cn:8443/mobile/#/pages/danger/checkTask/patrolRouteList?ctCode=CT260115000055&id=22494",
        "listurl": "https://ehs.sispark.com.cn:8443/api/v2/HDCheckTask/GetApiPageData?ctCode=CT260115000055&currStatus=do&page=0&limit=20&conditions=&dataType=PatrolRouteList"
    },
    {
        "now": "2026-01-16 23:57:52",
        "id": 22494,
        "RecordCode": "CT260115000055",
        "url": "https://ehs.sispark.com.cn:8443/mobile/#/pages/danger/checkTask/patrolRouteList?ctCode=CT260115000055&id=22494",
        "listurl": "https://ehs.sispark.com.cn:8443/api/v2/HDCheckTask/GetApiPageData?ctCode=CT260115000055&currStatus=do&page=0&limit=20&conditions=&dataType=PatrolRouteList"
    },
    {
        "now": "2026-01-16 23:57:53",
        "id": 22494,
        "RecordCode": "CT260115000055",
        "url": "https://ehs.sispark.com.cn:8443/mobile/#/pages/danger/checkTask/patrolRouteList?ctCode=CT260115000055&id=22494",
        "listurl": "https://ehs.sispark.com.cn:8443/api/v2/HDCheckTask/GetApiPageData?ctCode=CT260115000055&currStatus=do&page=0&limit=20&conditions=&dataType=PatrolRouteList"
    },
    {
        "now": "2026-01-16 23:57:53",
        "id": 22494,
        "RecordCode": "CT260115000055",
        "url": "https://ehs.sispark.com.cn:8443/mobile/#/pages/danger/checkTask/patrolRouteList?ctCode=CT260115000055&id=22494",
        "listurl": "https://ehs.sispark.com.cn:8443/api/v2/HDCheckTask/GetApiPageData?ctCode=CT260115000055&currStatus=do&page=0&limit=20&conditions=&dataType=PatrolRouteList"
    },
    {
        "now": "2026-01-16 23:57:58",
        "id": 22494,
        "RecordCode": "CT260115000055",
        "url": "https://ehs.sispark.com.cn:8443/mobile/#/pages/danger/checkTask/patrolRouteList?ctCode=CT260115000055&id=22494",
        "listurl": "https://ehs.sispark.com.cn:8443/api/v2/HDCheckTask/GetApiPageData?ctCode=CT260115000055&currStatus=do&page=0&limit=20&conditions=&dataType=PatrolRouteList"
    },
    {
        "now": "2026-01-16 23:58:02",
        "id": 22494,
        "RecordCode": "CT260115000055",
        "url": "https://ehs.sispark.com.cn:8443/mobile/#/pages/danger/checkTask/patrolRouteList?ctCode=CT260115000055&id=22494",
        "listurl": "https://ehs.sispark.com.cn:8443/api/v2/HDCheckTask/GetApiPageData?ctCode=CT260115000055&currStatus=do&page=0&limit=20&conditions=&dataType=PatrolRouteList"
    },
    {
        "now": "2026-01-16 23:58:04",
        "id": 22494,
        "RecordCode": "CT260115000055",
        "url": "https://ehs.sispark.com.cn:8443/mobile/#/pages/danger/checkTask/patrolRouteList?ctCode=CT260115000055&id=22494",
        "listurl": "https://ehs.sispark.com.cn:8443/api/v2/HDCheckTask/GetApiPageData?ctCode=CT260115000055&currStatus=do&page=0&limit=20&conditions=&dataType=PatrolRouteList"
    },
    {
        "now": "2026-01-16 23:58:04",
        "id": 22494,
        "RecordCode": "CT260115000055",
        "url": "https://ehs.sispark.com.cn:8443/mobile/#/pages/danger/checkTask/patrolRouteList?ctCode=CT260115000055&id=22494",
        "listurl": "https://ehs.sispark.com.cn:8443/api/v2/HDCheckTask/GetApiPageData?ctCode=CT260115000055&currStatus=do&page=0&limit=20&conditions=&dataType=PatrolRouteList"
    },
    {
        "now": "2026-01-16 23:58:09",
        "id": 22494,
        "RecordCode": "CT260115000055",
        "url": "https://ehs.sispark.com.cn:8443/mobile/#/pages/danger/checkTask/patrolRouteList?ctCode=CT260115000055&id=22494",
        "listurl": "https://ehs.sispark.com.cn:8443/api/v2/HDCheckTask/GetApiPageData?ctCode=CT260115000055&currStatus=do&page=0&limit=20&conditions=&dataType=PatrolRouteList"
    },
    {
        "now": "2026-01-16 23:58:14",
        "id": 22494,
        "RecordCode": "CT260115000055",
        "url": "https://ehs.sispark.com.cn:8443/mobile/#/pages/danger/checkTask/patrolRouteList?ctCode=CT260115000055&id=22494",
        "listurl": "https://ehs.sispark.com.cn:8443/api/v2/HDCheckTask/GetApiPageData?ctCode=CT260115000055&currStatus=do&page=0&limit=20&conditions=&dataType=PatrolRouteList"
    },
    {
        "now": "2026-01-16 23:58:14",
        "id": 22494,
        "RecordCode": "CT260115000055",
        "url": "https://ehs.sispark.com.cn:8443/mobile/#/pages/danger/checkTask/patrolRouteList?ctCode=CT260115000055&id=22494",
        "listurl": "https://ehs.sispark.com.cn:8443/api/v2/HDCheckTask/GetApiPageData?ctCode=CT260115000055&currStatus=do&page=0&limit=20&conditions=&dataType=PatrolRouteList"
    },
    {
        "now": "2026-01-16 23:58:15",
        "id": 22494,
        "RecordCode": "CT260115000055",
        "url": "https://ehs.sispark.com.cn:8443/mobile/#/pages/danger/checkTask/patrolRouteList?ctCode=CT260115000055&id=22494",
        "listurl": "https://ehs.sispark.com.cn:8443/api/v2/HDCheckTask/GetApiPageData?ctCode=CT260115000055&currStatus=do&page=0&limit=20&conditions=&dataType=PatrolRouteList"
    },
    {
        "now": "2026-01-16 23:58:15",
        "id": 22494,
        "RecordCode": "CT260115000055",
        "url": "https://ehs.sispark.com.cn:8443/mobile/#/pages/danger/checkTask/patrolRouteList?ctCode=CT260115000055&id=22494",
        "listurl": "https://ehs.sispark.com.cn:8443/api/v2/HDCheckTask/GetApiPageData?ctCode=CT260115000055&currStatus=do&page=0&limit=20&conditions=&dataType=PatrolRouteList"
    },
    {
        "now": "2026-01-16 23:58:20",
        "id": 22494,
        "RecordCode": "CT260115000055",
        "url": "https://ehs.sispark.com.cn:8443/mobile/#/pages/danger/checkTask/patrolRouteList?ctCode=CT260115000055&id=22494",
        "listurl": "https://ehs.sispark.com.cn:8443/api/v2/HDCheckTask/GetApiPageData?ctCode=CT260115000055&currStatus=do&page=0&limit=20&conditions=&dataType=PatrolRouteList"
    },
    {
        "now": "2026-01-16 23:58:22",
        "id": 22494,
        "RecordCode": "CT260115000055",
        "url": "https://ehs.sispark.com.cn:8443/mobile/#/pages/danger/checkTask/patrolRouteList?ctCode=CT260115000055&id=22494",
        "listurl": "https://ehs.sispark.com.cn:8443/api/v2/HDCheckTask/GetApiPageData?ctCode=CT260115000055&currStatus=do&page=0&limit=20&conditions=&dataType=PatrolRouteList"
    },
    {
        "now": "2026-01-16 23:58:25",
        "id": 22494,
        "RecordCode": "CT260115000055",
        "url": "https://ehs.sispark.com.cn:8443/mobile/#/pages/danger/checkTask/patrolRouteList?ctCode=CT260115000055&id=22494",
        "listurl": "https://ehs.sispark.com.cn:8443/api/v2/HDCheckTask/GetApiPageData?ctCode=CT260115000055&currStatus=do&page=0&limit=20&conditions=&dataType=PatrolRouteList"
    },
    {
        "now": "2026-01-16 23:58:31",
        "id": 22494,
        "RecordCode": "CT260115000055",
        "url": "https://ehs.sispark.com.cn:8443/mobile/#/pages/danger/checkTask/patrolRouteList?ctCode=CT260115000055&id=22494",
        "listurl": "https://ehs.sispark.com.cn:8443/api/v2/HDCheckTask/GetApiPageData?ctCode=CT260115000055&currStatus=do&page=0&limit=20&conditions=&dataType=PatrolRouteList"
    },
    {
        "now": "2026-01-16 23:58:36",
        "id": 22494,
        "RecordCode": "CT260115000055",
        "url": "https://ehs.sispark.com.cn:8443/mobile/#/pages/danger/checkTask/patrolRouteList?ctCode=CT260115000055&id=22494",
        "listurl": "https://ehs.sispark.com.cn:8443/api/v2/HDCheckTask/GetApiPageData?ctCode=CT260115000055&currStatus=do&page=0&limit=20&conditions=&dataType=PatrolRouteList"
    },
    {
        "now": "2026-01-16 23:58:38",
        "id": 22494,
        "RecordCode": "CT260115000055",
        "url": "https://ehs.sispark.com.cn:8443/mobile/#/pages/danger/checkTask/patrolRouteList?ctCode=CT260115000055&id=22494",
        "listurl": "https://ehs.sispark.com.cn:8443/api/v2/HDCheckTask/GetApiPageData?ctCode=CT260115000055&currStatus=do&page=0&limit=20&conditions=&dataType=PatrolRouteList"
    },
    {
        "now": "2026-01-16 23:58:41",
        "id": 22494,
        "RecordCode": "CT260115000055",
        "url": "https://ehs.sispark.com.cn:8443/mobile/#/pages/danger/checkTask/patrolRouteList?ctCode=CT260115000055&id=22494",
        "listurl": "https://ehs.sispark.com.cn:8443/api/v2/HDCheckTask/GetApiPageData?ctCode=CT260115000055&currStatus=do&page=0&limit=20&conditions=&dataType=PatrolRouteList"
    },
    {
        "now": "2026-01-16 23:58:47",
        "id": 22494,
        "RecordCode": "CT260115000055",
        "url": "https://ehs.sispark.com.cn:8443/mobile/#/pages/danger/checkTask/patrolRouteList?ctCode=CT260115000055&id=22494",
        "listurl": "https://ehs.sispark.com.cn:8443/api/v2/HDCheckTask/GetApiPageData?ctCode=CT260115000055&currStatus=do&page=0&limit=20&conditions=&dataType=PatrolRouteList"
    },
    {
        "now": "2026-01-16 23:58:48",
        "id": 22494,
        "RecordCode": "CT260115000055",
        "url": "https://ehs.sispark.com.cn:8443/mobile/#/pages/danger/checkTask/patrolRouteList?ctCode=CT260115000055&id=22494",
        "listurl": "https://ehs.sispark.com.cn:8443/api/v2/HDCheckTask/GetApiPageData?ctCode=CT260115000055&currStatus=do&page=0&limit=20&conditions=&dataType=PatrolRouteList"
    },
    {
        "now": "2026-01-16 23:58:48",
        "id": 22494,
        "RecordCode": "CT260115000055",
        "url": "https://ehs.sispark.com.cn:8443/mobile/#/pages/danger/checkTask/patrolRouteList?ctCode=CT260115000055&id=22494",
        "listurl": "https://ehs.sispark.com.cn:8443/api/v2/HDCheckTask/GetApiPageData?ctCode=CT260115000055&currStatus=do&page=0&limit=20&conditions=&dataType=PatrolRouteList"
    },
    {
        "now": "2026-01-16 23:58:48",
        "id": 22494,
        "RecordCode": "CT260115000055",
        "url": "https://ehs.sispark.com.cn:8443/mobile/#/pages/danger/checkTask/patrolRouteList?ctCode=CT260115000055&id=22494",
        "listurl": "https://ehs.sispark.com.cn:8443/api/v2/HDCheckTask/GetApiPageData?ctCode=CT260115000055&currStatus=do&page=0&limit=20&conditions=&dataType=PatrolRouteList"
    },
    {
        "now": "2026-01-16 23:58:49",
        "id": 22494,
        "RecordCode": "CT260115000055",
        "url": "https://ehs.sispark.com.cn:8443/mobile/#/pages/danger/checkTask/patrolRouteList?ctCode=CT260115000055&id=22494",
        "listurl": "https://ehs.sispark.com.cn:8443/api/v2/HDCheckTask/GetApiPageData?ctCode=CT260115000055&currStatus=do&page=0&limit=20&conditions=&dataType=PatrolRouteList"
    },
    {
        "now": "2026-01-16 23:58:49",
        "id": 22494,
        "RecordCode": "CT260115000055",
        "url": "https://ehs.sispark.com.cn:8443/mobile/#/pages/danger/checkTask/patrolRouteList?ctCode=CT260115000055&id=22494",
        "listurl": "https://ehs.sispark.com.cn:8443/api/v2/HDCheckTask/GetApiPageData?ctCode=CT260115000055&currStatus=do&page=0&limit=20&conditions=&dataType=PatrolRouteList"
    },
    {
        "now": "2026-01-16 23:58:49",
        "id": 22494,
        "RecordCode": "CT260115000055",
        "url": "https://ehs.sispark.com.cn:8443/mobile/#/pages/danger/checkTask/patrolRouteList?ctCode=CT260115000055&id=22494",
        "listurl": "https://ehs.sispark.com.cn:8443/api/v2/HDCheckTask/GetApiPageData?ctCode=CT260115000055&currStatus=do&page=0&limit=20&conditions=&dataType=PatrolRouteList"
    },
    {
        "now": "2026-01-16 23:58:50",
        "id": 22494,
        "RecordCode": "CT260115000055",
        "url": "https://ehs.sispark.com.cn:8443/mobile/#/pages/danger/checkTask/patrolRouteList?ctCode=CT260115000055&id=22494",
        "listurl": "https://ehs.sispark.com.cn:8443/api/v2/HDCheckTask/GetApiPageData?ctCode=CT260115000055&currStatus=do&page=0&limit=20&conditions=&dataType=PatrolRouteList"
    },
    {
        "now": "2026-01-16 23:58:50",
        "id": 22494,
        "RecordCode": "CT260115000055",
        "url": "https://ehs.sispark.com.cn:8443/mobile/#/pages/danger/checkTask/patrolRouteList?ctCode=CT260115000055&id=22494",
        "listurl": "https://ehs.sispark.com.cn:8443/api/v2/HDCheckTask/GetApiPageData?ctCode=CT260115000055&currStatus=do&page=0&limit=20&conditions=&dataType=PatrolRouteList"
    },
    {
        "now": "2026-01-16 23:58:50",
        "id": 22494,
        "RecordCode": "CT260115000055",
        "url": "https://ehs.sispark.com.cn:8443/mobile/#/pages/danger/checkTask/patrolRouteList?ctCode=CT260115000055&id=22494",
        "listurl": "https://ehs.sispark.com.cn:8443/api/v2/HDCheckTask/GetApiPageData?ctCode=CT260115000055&currStatus=do&page=0&limit=20&conditions=&dataType=PatrolRouteList"
    },
    {
        "now": "2026-01-16 23:58:50",
        "id": 22494,
        "RecordCode": "CT260115000055",
        "url": "https://ehs.sispark.com.cn:8443/mobile/#/pages/danger/checkTask/patrolRouteList?ctCode=CT260115000055&id=22494",
        "listurl": "https://ehs.sispark.com.cn:8443/api/v2/HDCheckTask/GetApiPageData?ctCode=CT260115000055&currStatus=do&page=0&limit=20&conditions=&dataType=PatrolRouteList"
    },
    {
        "now": "2026-01-16 23:58:50",
        "id": 22494,
        "RecordCode": "CT260115000055",
        "url": "https://ehs.sispark.com.cn:8443/mobile/#/pages/danger/checkTask/patrolRouteList?ctCode=CT260115000055&id=22494",
        "listurl": "https://ehs.sispark.com.cn:8443/api/v2/HDCheckTask/GetApiPageData?ctCode=CT260115000055&currStatus=do&page=0&limit=20&conditions=&dataType=PatrolRouteList"
    },
    {
        "now": "2026-01-16 23:58:51",
        "id": 22494,
        "RecordCode": "CT260115000055",
        "url": "https://ehs.sispark.com.cn:8443/mobile/#/pages/danger/checkTask/patrolRouteList?ctCode=CT260115000055&id=22494",
        "listurl": "https://ehs.sispark.com.cn:8443/api/v2/HDCheckTask/GetApiPageData?ctCode=CT260115000055&currStatus=do&page=0&limit=20&conditions=&dataType=PatrolRouteList"
    },
    {
        "now": "2026-01-16 23:58:52",
        "id": 22494,
        "RecordCode": "CT260115000055",
        "url": "https://ehs.sispark.com.cn:8443/mobile/#/pages/danger/checkTask/patrolRouteList?ctCode=CT260115000055&id=22494",
        "listurl": "https://ehs.sispark.com.cn:8443/api/v2/HDCheckTask/GetApiPageData?ctCode=CT260115000055&currStatus=do&page=0&limit=20&conditions=&dataType=PatrolRouteList"
    },
    {
        "now": "2026-01-16 23:58:53",
        "id": 22494,
        "RecordCode": "CT260115000055",
        "url": "https://ehs.sispark.com.cn:8443/mobile/#/pages/danger/checkTask/patrolRouteList?ctCode=CT260115000055&id=22494",
        "listurl": "https://ehs.sispark.com.cn:8443/api/v2/HDCheckTask/GetApiPageData?ctCode=CT260115000055&currStatus=do&page=0&limit=20&conditions=&dataType=PatrolRouteList"
    },
    {
        "now": "2026-01-16 23:58:53",
        "id": 22494,
        "RecordCode": "CT260115000055",
        "url": "https://ehs.sispark.com.cn:8443/mobile/#/pages/danger/checkTask/patrolRouteList?ctCode=CT260115000055&id=22494",
        "listurl": "https://ehs.sispark.com.cn:8443/api/v2/HDCheckTask/GetApiPageData?ctCode=CT260115000055&currStatus=do&page=0&limit=20&conditions=&dataType=PatrolRouteList"
    },
    {
        "now": "2026-01-16 23:58:54",
        "id": 22494,
        "RecordCode": "CT260115000055",
        "url": "https://ehs.sispark.com.cn:8443/mobile/#/pages/danger/checkTask/patrolRouteList?ctCode=CT260115000055&id=22494",
        "listurl": "https://ehs.sispark.com.cn:8443/api/v2/HDCheckTask/GetApiPageData?ctCode=CT260115000055&currStatus=do&page=0&limit=20&conditions=&dataType=PatrolRouteList"
    },
    {
        "now": "2026-01-16 23:58:58",
        "id": 22494,
        "RecordCode": "CT260115000055",
        "url": "https://ehs.sispark.com.cn:8443/mobile/#/pages/danger/checkTask/patrolRouteList?ctCode=CT260115000055&id=22494",
        "listurl": "https://ehs.sispark.com.cn:8443/api/v2/HDCheckTask/GetApiPageData?ctCode=CT260115000055&currStatus=do&page=0&limit=20&conditions=&dataType=PatrolRouteList"
    },
    {
        "now": "2026-01-16 23:59:03",
        "id": 22494,
        "RecordCode": "CT260115000055",
        "url": "https://ehs.sispark.com.cn:8443/mobile/#/pages/danger/checkTask/patrolRouteList?ctCode=CT260115000055&id=22494",
        "listurl": "https://ehs.sispark.com.cn:8443/api/v2/HDCheckTask/GetApiPageData?ctCode=CT260115000055&currStatus=do&page=0&limit=20&conditions=&dataType=PatrolRouteList"
    },
    {
        "now": "2026-01-16 23:59:03",
        "id": 22494,
        "RecordCode": "CT260115000055",
        "url": "https://ehs.sispark.com.cn:8443/mobile/#/pages/danger/checkTask/patrolRouteList?ctCode=CT260115000055&id=22494",
        "listurl": "https://ehs.sispark.com.cn:8443/api/v2/HDCheckTask/GetApiPageData?ctCode=CT260115000055&currStatus=do&page=0&limit=20&conditions=&dataType=PatrolRouteList"
    },
    {
        "now": "2026-01-16 23:59:04",
        "id": 22494,
        "RecordCode": "CT260115000055",
        "url": "https://ehs.sispark.com.cn:8443/mobile/#/pages/danger/checkTask/patrolRouteList?ctCode=CT260115000055&id=22494",
        "listurl": "https://ehs.sispark.com.cn:8443/api/v2/HDCheckTask/GetApiPageData?ctCode=CT260115000055&currStatus=do&page=0&limit=20&conditions=&dataType=PatrolRouteList"
    },
    {
        "now": "2026-01-16 23:59:08",
        "id": 22494,
        "RecordCode": "CT260115000055",
        "url": "https://ehs.sispark.com.cn:8443/mobile/#/pages/danger/checkTask/patrolRouteList?ctCode=CT260115000055&id=22494",
        "listurl": "https://ehs.sispark.com.cn:8443/api/v2/HDCheckTask/GetApiPageData?ctCode=CT260115000055&currStatus=do&page=0&limit=20&conditions=&dataType=PatrolRouteList"
    },
    {
        "now": "2026-01-16 23:59:14",
        "id": 22494,
        "RecordCode": "CT260115000055",
        "url": "https://ehs.sispark.com.cn:8443/mobile/#/pages/danger/checkTask/patrolRouteList?ctCode=CT260115000055&id=22494",
        "listurl": "https://ehs.sispark.com.cn:8443/api/v2/HDCheckTask/GetApiPageData?ctCode=CT260115000055&currStatus=do&page=0&limit=20&conditions=&dataType=PatrolRouteList"
    },
    {
        "now": "2026-01-16 23:59:15",
        "id": 22494,
        "RecordCode": "CT260115000055",
        "url": "https://ehs.sispark.com.cn:8443/mobile/#/pages/danger/checkTask/patrolRouteList?ctCode=CT260115000055&id=22494",
        "listurl": "https://ehs.sispark.com.cn:8443/api/v2/HDCheckTask/GetApiPageData?ctCode=CT260115000055&currStatus=do&page=0&limit=20&conditions=&dataType=PatrolRouteList"
    },
    {
        "now": "2026-01-16 23:59:16",
        "id": 22494,
        "RecordCode": "CT260115000055",
        "url": "https://ehs.sispark.com.cn:8443/mobile/#/pages/danger/checkTask/patrolRouteList?ctCode=CT260115000055&id=22494",
        "listurl": "https://ehs.sispark.com.cn:8443/api/v2/HDCheckTask/GetApiPageData?ctCode=CT260115000055&currStatus=do&page=0&limit=20&conditions=&dataType=PatrolRouteList"
    },
    {
        "now": "2026-01-16 23:59:16",
        "id": 22494,
        "RecordCode": "CT260115000055",
        "url": "https://ehs.sispark.com.cn:8443/mobile/#/pages/danger/checkTask/patrolRouteList?ctCode=CT260115000055&id=22494",
        "listurl": "https://ehs.sispark.com.cn:8443/api/v2/HDCheckTask/GetApiPageData?ctCode=CT260115000055&currStatus=do&page=0&limit=20&conditions=&dataType=PatrolRouteList"
    },
    {
        "now": "2026-01-16 23:59:19",
        "id": 22494,
        "RecordCode": "CT260115000055",
        "url": "https://ehs.sispark.com.cn:8443/mobile/#/pages/danger/checkTask/patrolRouteList?ctCode=CT260115000055&id=22494",
        "listurl": "https://ehs.sispark.com.cn:8443/api/v2/HDCheckTask/GetApiPageData?ctCode=CT260115000055&currStatus=do&page=0&limit=20&conditions=&dataType=PatrolRouteList"
    },
    {
        "now": "2026-01-16 23:59:22",
        "id": 22494,
        "RecordCode": "CT260115000055",
        "url": "https://ehs.sispark.com.cn:8443/mobile/#/pages/danger/checkTask/patrolRouteList?ctCode=CT260115000055&id=22494",
        "listurl": "https://ehs.sispark.com.cn:8443/api/v2/HDCheckTask/GetApiPageData?ctCode=CT260115000055&currStatus=do&page=0&limit=20&conditions=&dataType=PatrolRouteList"
    },
    {
        "now": "2026-01-16 23:59:25",
        "id": 22494,
        "RecordCode": "CT260115000055",
        "url": "https://ehs.sispark.com.cn:8443/mobile/#/pages/danger/checkTask/patrolRouteList?ctCode=CT260115000055&id=22494",
        "listurl": "https://ehs.sispark.com.cn:8443/api/v2/HDCheckTask/GetApiPageData?ctCode=CT260115000055&currStatus=do&page=0&limit=20&conditions=&dataType=PatrolRouteList"
    },
    {
        "now": "2026-01-16 23:59:30",
        "id": 22494,
        "RecordCode": "CT260115000055",
        "url": "https://ehs.sispark.com.cn:8443/mobile/#/pages/danger/checkTask/patrolRouteList?ctCode=CT260115000055&id=22494",
        "listurl": "https://ehs.sispark.com.cn:8443/api/v2/HDCheckTask/GetApiPageData?ctCode=CT260115000055&currStatus=do&page=0&limit=20&conditions=&dataType=PatrolRouteList"
    },
    {
        "now": "2026-01-16 23:59:36",
        "id": 22494,
        "RecordCode": "CT260115000055",
        "url": "https://ehs.sispark.com.cn:8443/mobile/#/pages/danger/checkTask/patrolRouteList?ctCode=CT260115000055&id=22494",
        "listurl": "https://ehs.sispark.com.cn:8443/api/v2/HDCheckTask/GetApiPageData?ctCode=CT260115000055&currStatus=do&page=0&limit=20&conditions=&dataType=PatrolRouteList"
    },
    {
        "now": "2026-01-16 23:59:39",
        "id": 22494,
        "RecordCode": "CT260115000055",
        "url": "https://ehs.sispark.com.cn:8443/mobile/#/pages/danger/checkTask/patrolRouteList?ctCode=CT260115000055&id=22494",
        "listurl": "https://ehs.sispark.com.cn:8443/api/v2/HDCheckTask/GetApiPageData?ctCode=CT260115000055&currStatus=do&page=0&limit=20&conditions=&dataType=PatrolRouteList"
    },
    {
        "now": "2026-01-16 23:59:41",
        "id": 22494,
        "RecordCode": "CT260115000055",
        "url": "https://ehs.sispark.com.cn:8443/mobile/#/pages/danger/checkTask/patrolRouteList?ctCode=CT260115000055&id=22494",
        "listurl": "https://ehs.sispark.com.cn:8443/api/v2/HDCheckTask/GetApiPageData?ctCode=CT260115000055&currStatus=do&page=0&limit=20&conditions=&dataType=PatrolRouteList"
    },
    {
        "now": "2026-01-16 23:59:46",
        "id": 22494,
        "RecordCode": "CT260115000055",
        "url": "https://ehs.sispark.com.cn:8443/mobile/#/pages/danger/checkTask/patrolRouteList?ctCode=CT260115000055&id=22494",
        "listurl": "https://ehs.sispark.com.cn:8443/api/v2/HDCheckTask/GetApiPageData?ctCode=CT260115000055&currStatus=do&page=0&limit=20&conditions=&dataType=PatrolRouteList"
    },
    {
        "now": "2026-01-16 23:59:48",
        "id": 22494,
        "RecordCode": "CT260115000055",
        "url": "https://ehs.sispark.com.cn:8443/mobile/#/pages/danger/checkTask/patrolRouteList?ctCode=CT260115000055&id=22494",
        "listurl": "https://ehs.sispark.com.cn:8443/api/v2/HDCheckTask/GetApiPageData?ctCode=CT260115000055&currStatus=do&page=0&limit=20&conditions=&dataType=PatrolRouteList"
    },
    {
        "now": "2026-01-16 23:59:48",
        "id": 22494,
        "RecordCode": "CT260115000055",
        "url": "https://ehs.sispark.com.cn:8443/mobile/#/pages/danger/checkTask/patrolRouteList?ctCode=CT260115000055&id=22494",
        "listurl": "https://ehs.sispark.com.cn:8443/api/v2/HDCheckTask/GetApiPageData?ctCode=CT260115000055&currStatus=do&page=0&limit=20&conditions=&dataType=PatrolRouteList"
    },
    {
        "now": "2026-01-16 23:59:48",
        "id": 22494,
        "RecordCode": "CT260115000055",
        "url": "https://ehs.sispark.com.cn:8443/mobile/#/pages/danger/checkTask/patrolRouteList?ctCode=CT260115000055&id=22494",
        "listurl": "https://ehs.sispark.com.cn:8443/api/v2/HDCheckTask/GetApiPageData?ctCode=CT260115000055&currStatus=do&page=0&limit=20&conditions=&dataType=PatrolRouteList"
    },
    {
        "now": "2026-01-16 23:59:49",
        "id": 22494,
        "RecordCode": "CT260115000055",
        "url": "https://ehs.sispark.com.cn:8443/mobile/#/pages/danger/checkTask/patrolRouteList?ctCode=CT260115000055&id=22494",
        "listurl": "https://ehs.sispark.com.cn:8443/api/v2/HDCheckTask/GetApiPageData?ctCode=CT260115000055&currStatus=do&page=0&limit=20&conditions=&dataType=PatrolRouteList"
    },
    {
        "now": "2026-01-16 23:59:49",
        "id": 22494,
        "RecordCode": "CT260115000055",
        "url": "https://ehs.sispark.com.cn:8443/mobile/#/pages/danger/checkTask/patrolRouteList?ctCode=CT260115000055&id=22494",
        "listurl": "https://ehs.sispark.com.cn:8443/api/v2/HDCheckTask/GetApiPageData?ctCode=CT260115000055&currStatus=do&page=0&limit=20&conditions=&dataType=PatrolRouteList"
    },
    {
        "now": "2026-01-16 23:59:50",
        "id": 22494,
        "RecordCode": "CT260115000055",
        "url": "https://ehs.sispark.com.cn:8443/mobile/#/pages/danger/checkTask/patrolRouteList?ctCode=CT260115000055&id=22494",
        "listurl": "https://ehs.sispark.com.cn:8443/api/v2/HDCheckTask/GetApiPageData?ctCode=CT260115000055&currStatus=do&page=0&limit=20&conditions=&dataType=PatrolRouteList"
    },
    {
        "now": "2026-01-16 23:59:50",
        "id": 22494,
        "RecordCode": "CT260115000055",
        "url": "https://ehs.sispark.com.cn:8443/mobile/#/pages/danger/checkTask/patrolRouteList?ctCode=CT260115000055&id=22494",
        "listurl": "https://ehs.sispark.com.cn:8443/api/v2/HDCheckTask/GetApiPageData?ctCode=CT260115000055&currStatus=do&page=0&limit=20&conditions=&dataType=PatrolRouteList"
    },
    {
        "now": "2026-01-16 23:59:50",
        "id": 22494,
        "RecordCode": "CT260115000055",
        "url": "https://ehs.sispark.com.cn:8443/mobile/#/pages/danger/checkTask/patrolRouteList?ctCode=CT260115000055&id=22494",
        "listurl": "https://ehs.sispark.com.cn:8443/api/v2/HDCheckTask/GetApiPageData?ctCode=CT260115000055&currStatus=do&page=0&limit=20&conditions=&dataType=PatrolRouteList"
    },
    {
        "now": "2026-01-16 23:59:51",
        "id": 22494,
        "RecordCode": "CT260115000055",
        "url": "https://ehs.sispark.com.cn:8443/mobile/#/pages/danger/checkTask/patrolRouteList?ctCode=CT260115000055&id=22494",
        "listurl": "https://ehs.sispark.com.cn:8443/api/v2/HDCheckTask/GetApiPageData?ctCode=CT260115000055&currStatus=do&page=0&limit=20&conditions=&dataType=PatrolRouteList"
    },
    {
        "now": "2026-01-16 23:59:51",
        "id": 22494,
        "RecordCode": "CT260115000055",
        "url": "https://ehs.sispark.com.cn:8443/mobile/#/pages/danger/checkTask/patrolRouteList?ctCode=CT260115000055&id=22494",
        "listurl": "https://ehs.sispark.com.cn:8443/api/v2/HDCheckTask/GetApiPageData?ctCode=CT260115000055&currStatus=do&page=0&limit=20&conditions=&dataType=PatrolRouteList"
    },
    {
        "now": "2026-01-16 23:59:51",
        "id": 22494,
        "RecordCode": "CT260115000055",
        "url": "https://ehs.sispark.com.cn:8443/mobile/#/pages/danger/checkTask/patrolRouteList?ctCode=CT260115000055&id=22494",
        "listurl": "https://ehs.sispark.com.cn:8443/api/v2/HDCheckTask/GetApiPageData?ctCode=CT260115000055&currStatus=do&page=0&limit=20&conditions=&dataType=PatrolRouteList"
    },
    {
        "now": "2026-01-16 23:59:52",
        "id": 22494,
        "RecordCode": "CT260115000055",
        "url": "https://ehs.sispark.com.cn:8443/mobile/#/pages/danger/checkTask/patrolRouteList?ctCode=CT260115000055&id=22494",
        "listurl": "https://ehs.sispark.com.cn:8443/api/v2/HDCheckTask/GetApiPageData?ctCode=CT260115000055&currStatus=do&page=0&limit=20&conditions=&dataType=PatrolRouteList"
    },
    {
        "now": "2026-01-16 23:59:52",
        "id": 22494,
        "RecordCode": "CT260115000055",
        "url": "https://ehs.sispark.com.cn:8443/mobile/#/pages/danger/checkTask/patrolRouteList?ctCode=CT260115000055&id=22494",
        "listurl": "https://ehs.sispark.com.cn:8443/api/v2/HDCheckTask/GetApiPageData?ctCode=CT260115000055&currStatus=do&page=0&limit=20&conditions=&dataType=PatrolRouteList"
    },
    {
        "now": "2026-01-16 23:59:53",
        "id": 22494,
        "RecordCode": "CT260115000055",
        "url": "https://ehs.sispark.com.cn:8443/mobile/#/pages/danger/checkTask/patrolRouteList?ctCode=CT260115000055&id=22494",
        "listurl": "https://ehs.sispark.com.cn:8443/api/v2/HDCheckTask/GetApiPageData?ctCode=CT260115000055&currStatus=do&page=0&limit=20&conditions=&dataType=PatrolRouteList"
    },
    {
        "now": "2026-01-16 23:59:53",
        "id": 22494,
        "RecordCode": "CT260115000055",
        "url": "https://ehs.sispark.com.cn:8443/mobile/#/pages/danger/checkTask/patrolRouteList?ctCode=CT260115000055&id=22494",
        "listurl": "https://ehs.sispark.com.cn:8443/api/v2/HDCheckTask/GetApiPageData?ctCode=CT260115000055&currStatus=do&page=0&limit=20&conditions=&dataType=PatrolRouteList"
    },
    {
        "now": "2026-01-16 23:59:54",
        "id": 22494,
        "RecordCode": "CT260115000055",
        "url": "https://ehs.sispark.com.cn:8443/mobile/#/pages/danger/checkTask/patrolRouteList?ctCode=CT260115000055&id=22494",
        "listurl": "https://ehs.sispark.com.cn:8443/api/v2/HDCheckTask/GetApiPageData?ctCode=CT260115000055&currStatus=do&page=0&limit=20&conditions=&dataType=PatrolRouteList"
    },
    {
        "now": "2026-01-16 23:59:57",
        "id": 22494,
        "RecordCode": "CT260115000055",
        "url": "https://ehs.sispark.com.cn:8443/mobile/#/pages/danger/checkTask/patrolRouteList?ctCode=CT260115000055&id=22494",
        "listurl": "https://ehs.sispark.com.cn:8443/api/v2/HDCheckTask/GetApiPageData?ctCode=CT260115000055&currStatus=do&page=0&limit=20&conditions=&dataType=PatrolRouteList"
    }
]