[
    {
        "now": "2026-03-23 16:50:23",
        "id": 25608,
        "RecordCode": "CT260322000025",
        "url": "https://ehs.sispark.com.cn:8443/mobile/#/pages/danger/checkTask/patrolRouteList?ctCode=CT260322000025&id=25608",
        "listurl": "https://ehs.sispark.com.cn:8443/api/v2/HDCheckTask/GetApiPageData?ctCode=CT260322000025&currStatus=do&page=0&limit=20&conditions=&dataType=PatrolRouteList"
    },
    {
        "now": "2026-03-23 16:50:23",
        "id": 25608,
        "RecordCode": "CT260322000025",
        "url": "https://ehs.sispark.com.cn:8443/mobile/#/pages/danger/checkTask/patrolRouteList?ctCode=CT260322000025&id=25608",
        "listurl": "https://ehs.sispark.com.cn:8443/api/v2/HDCheckTask/GetApiPageData?ctCode=CT260322000025&currStatus=do&page=0&limit=20&conditions=&dataType=PatrolRouteList"
    },
    {
        "now": "2026-03-23 16:51:04",
        "id": 25608,
        "RecordCode": "CT260322000025",
        "url": "https://ehs.sispark.com.cn:8443/mobile/#/pages/danger/checkTask/patrolRouteList?ctCode=CT260322000025&id=25608",
        "listurl": "https://ehs.sispark.com.cn:8443/api/v2/HDCheckTask/GetApiPageData?ctCode=CT260322000025&currStatus=do&page=0&limit=20&conditions=&dataType=PatrolRouteList"
    },
    {
        "now": "2026-03-23 16:51:04",
        "id": 25608,
        "RecordCode": "CT260322000025",
        "url": "https://ehs.sispark.com.cn:8443/mobile/#/pages/danger/checkTask/patrolRouteList?ctCode=CT260322000025&id=25608",
        "listurl": "https://ehs.sispark.com.cn:8443/api/v2/HDCheckTask/GetApiPageData?ctCode=CT260322000025&currStatus=do&page=0&limit=20&conditions=&dataType=PatrolRouteList"
    },
    {
        "now": "2026-03-23 16:52:05",
        "id": 24492,
        "RecordCode": "CT260228000014",
        "url": "https://ehs.sispark.com.cn:8443/mobile/#/pages/danger/checkTask/patrolRouteList?ctCode=CT260228000014&id=24492",
        "listurl": "https://ehs.sispark.com.cn:8443/api/v2/HDCheckTask/GetApiPageData?ctCode=CT260228000014&currStatus=do&page=0&limit=20&conditions=&dataType=PatrolRouteList"
    },
    {
        "now": "2026-03-23 16:52:05",
        "id": 24492,
        "RecordCode": "CT260228000014",
        "url": "https://ehs.sispark.com.cn:8443/mobile/#/pages/danger/checkTask/patrolRouteList?ctCode=CT260228000014&id=24492",
        "listurl": "https://ehs.sispark.com.cn:8443/api/v2/HDCheckTask/GetApiPageData?ctCode=CT260228000014&currStatus=do&page=0&limit=20&conditions=&dataType=PatrolRouteList"
    },
    {
        "now": "2026-03-23 16:53:07",
        "id": 25608,
        "RecordCode": "CT260322000025",
        "url": "https://ehs.sispark.com.cn:8443/mobile/#/pages/danger/checkTask/patrolRouteList?ctCode=CT260322000025&id=25608",
        "listurl": "https://ehs.sispark.com.cn:8443/api/v2/HDCheckTask/GetApiPageData?ctCode=CT260322000025&currStatus=do&page=0&limit=20&conditions=&dataType=PatrolRouteList"
    },
    {
        "now": "2026-03-23 16:53:07",
        "id": 25608,
        "RecordCode": "CT260322000025",
        "url": "https://ehs.sispark.com.cn:8443/mobile/#/pages/danger/checkTask/patrolRouteList?ctCode=CT260322000025&id=25608",
        "listurl": "https://ehs.sispark.com.cn:8443/api/v2/HDCheckTask/GetApiPageData?ctCode=CT260322000025&currStatus=do&page=0&limit=20&conditions=&dataType=PatrolRouteList"
    }
]